LICENSE.txt
MANIFEST.in
README.rst
TODO.txt
VERSION.txt
setup.cfg
setup.py
pysyncml/__init__.py
pysyncml/codec.py
pysyncml/common.py
pysyncml/constants.py
pysyncml/context.py
pysyncml/ctype.py
pysyncml/i18n.py
pysyncml/matcher.py
pysyncml/protocol.py
pysyncml/router.py
pysyncml/smp.py
pysyncml/state.py
pysyncml/synchronizer.py
pysyncml/test_client.py
pysyncml/test_codec.py
pysyncml/test_common.py
pysyncml/test_ctype.py
pysyncml/test_helpers.py
pysyncml/test_server.py
pysyncml/test_treeclient.py
pysyncml.egg-info/PKG-INFO
pysyncml.egg-info/SOURCES.txt
pysyncml.egg-info/dependency_links.txt
pysyncml.egg-info/entry_points.txt
pysyncml.egg-info/requires.txt
pysyncml.egg-info/top_level.txt
pysyncml.egg-info/zip-safe
pysyncml/agents/__init__.py
pysyncml/agents/base.py
pysyncml/agents/file.py
pysyncml/agents/note.py
pysyncml/agents/test_file.py
pysyncml/agents/test_note.py
pysyncml/change/__init__.py
pysyncml/change/merger.py
pysyncml/change/test_merger.py
pysyncml/change/test_tracker.py
pysyncml/change/tracker.py
pysyncml/cli/__init__.py
pysyncml/cli/base.py
pysyncml/cli/files.py
pysyncml/cli/notes.py
pysyncml/items/__init__.py
pysyncml/items/base.py
pysyncml/items/file.py
pysyncml/items/folder.py
pysyncml/items/note.py
pysyncml/items/test_file.py
pysyncml/items/test_folder.py
pysyncml/items/test_note.py
pysyncml/model/__init__.py
pysyncml/model/adapter.py
pysyncml/model/devinfo.py
pysyncml/model/mapping.py
pysyncml/model/store.py