Metadata-Version: 1.1
Name: pysyncml
Version: 0.2.0
Summary: A pure-python implementation of the SyncML adapter framework and protocol.
Home-page: http://github.com/metagriffin/pysyncml
Author: metagriffin
Author-email: mg.pypi@uberdev.org
License: GPLv3+
Keywords: syncml python synchronize mobile desktop framework adapter open mobile alliance contacts agenda calendar files notes
Platform: any
Classifier: Development Status :: 4 - Beta
Classifier: Intended Audience :: Developers
Classifier: Natural Language :: English
Classifier: Operating System :: OS Independent
Classifier: Programming Language :: Python
Classifier: Topic :: Internet
Classifier: Topic :: Other/Nonlisted Topic
Classifier: Topic :: Software Development
Classifier: Topic :: Software Development :: Libraries :: Python Modules
Classifier: Topic :: System :: Distributed Computing
Classifier: Topic :: System :: Filesystems
Classifier: Topic :: Utilities
Classifier: License :: OSI Approved :: GNU General Public License v3 or later (GPLv3+)
